[{"geometry": {"type": "MultiPoint", "coordinates": [[1480.8424072265625, 1098.7344970703125], [1488.3125, 1104.0462646484375], [1466.302490234375, 1124.600341796875], [1460.8214111328125, 1105.587890625]]}, "properties": {"annotation_uuid": "20e7f082-08ce-4629-89ce-62ddb8e4b10b", "unclear": true, "class": "unclear"}}, {"geometry": {"type": "MultiPoint", "coordinates": [[2447.18505859375, 697.1557006835938], [2553.434673437082, 799.9492513025091], [2456.780517578125, 905.1870727539062], [2347.614990234375, 799.548095703125]]}, "properties": {"annotation_uuid": "81a8c5e8-b591-4bc9-94d6-4fefb8ea8dd2", "unclear": false, "is_sticker": false, "is_for_ego_road": "Inconclusive", "is_for_other_traffic_participant": "Inconclusive", "complementary_to_landmark": "Inconclusive", "class": "Prohibitory_MaximumSpeedLimit30Begin", "is_for_ego_lane": "Inconclusive", "contains_inner_signs": false, "is_on_dynamic_object": false, "is_for_construction": false, "occlusion_ratio": "None", "is_electronic": false}}, {"geometry": {"type": "MultiPoint", "coordinates": [[2124.16455078125, 1033.156494140625], [2118.437255859375, 1036.44970703125], [2122.159912109375, 1040.1724853515625], [2128.8896484375, 1036.44970703125]]}, "properties": {"annotation_uuid": "6f761d4c-a5d6-4b1e-8da6-25991e6957eb", "unclear": true, "class": "unclear"}}]